{
	"info": {
		"_postman_id": "a86bbb12-c8a9-4b35-8a88-19af08a246a7",
		"name": "gokul_carts",
		"schema": "https://schema.getpostman.com/json/collection/v2.1.0/collection.json",
		"_exporter_id": "50248252",
		"_collection_link": "https://gokulchandran00621-1452516.postman.co/workspace/Gokul-Chandran's-Workspace~da0c8ec1-ec55-49ac-8bf1-33355f020597/collection/50248252-a86bbb12-c8a9-4b35-8a88-19af08a246a7?action=share&source=collection_link&creator=50248252"
	},
	"item": [
		{
			"name": "Get all",
			"event": [
				{
					"listen": "test",
					"script": {
						"exec": [
							"pm.collectionVariables.set(\"id\", pm.response.json().id)\r",
							"\r",
							"pm.test(\"status code verify\",function()\r",
							"{\r",
							"    pm.response.to.have.status(200);\r",
							"});\r",
							"pm.test(\"status message verify\" ,function()\r",
							"{\r",
							"    pm.response.to.have.status(\"OK\");\r",
							"});\r",
							"pm.test(\"status code within range\", function () {\r",
							"    pm.expect(pm.response.code).to.be.within(200, 404);\r",
							"});\r",
							"pm.test(\"Range of the status code verify\", function()\r",
							"{\r",
							"    pm.expect(pm.response.code).to.be.oneOf([200,201,205]);\r",
							"})\r",
							"pm.test(\"status code below verify\", function()\r",
							"{\r",
							"    pm.expect(pm.response.code).to.be.below(202);\r",
							"})\r",
							"pm.test(\"status code above verify\", function()\r",
							"{\r",
							"    pm.expect(pm.response.code).to.be.above(199);\r",
							"})\r",
							"pm.test(\"Verify response time\", function()\r",
							"{\r",
							"    pm.expect(pm.response.responseTime).to.be.below(3000);\r",
							"})\r",
							"pm.test(\"Verify response time\", function()\r",
							"{\r",
							"    pm.expect(pm.response.responseTime).to.be.above(200);\r",
							"})\r",
							"pm.test(\"check content type header is present\" , function()\r",
							"{\r",
							"    pm.response.to.have.header(\"Content-type\");\r",
							"})\r",
							"pm.test(\"check value of content-type\" , function()\r",
							"{\r",
							"    pm.expect(pm.response.headers.get(\"Content-type\")).to.eql(\"application/json\");\r",
							"})\r",
							"pm.test(\"check vaue of content-type\" , function()\r",
							"{\r",
							"    pm.expect(pm.response.headers.get(\"Content-type\")).to.include(\"son\");\r",
							"})\r",
							"pm.test(\"check multiple headers\", function() {\r",
							"    const data = [\"content-length\", \"content-type\", \"date\"]\r",
							"    data.forEach(function(item) {\r",
							"        pm.response.to.have.header(item);\r",
							"    })\r",
							"})\r",
							"pm.test(\"test status code using if-else\", function() {\r",
							"    const data = pm.response.code\r",
							"    if (data === 200) {\r",
							"        pm.response.to.have.status(\"OK\")\r",
							"    } else {\r",
							"        pm.response.to.have.status(\"Not Found\")\r",
							"    }\r",
							"})\r",
							"\r",
							"pm.test(\"status code is not in oneof function\", function() {\r",
							"    pm.expect(pm.response.code).to.not.be.oneOf([ 202, 203, 204, 205, 206, 207]);\r",
							"})\r",
							"\r",
							"pm.test(\"content-length value check\", function() {\r",
							"    let data = pm.response.headers.get(\"content-length\")\r",
							"    pm.expect(Number(data)).to.not.eql(0)\r",
							"})\r",
							"\r",
							"\r",
							"// test response body:\r",
							"pm.test(\"response exist or not\", function() {\r",
							"    pm.expect(pm.response.text()).to.not.be.empty\r",
							"})\r",
							"\r",
							"pm.test(\"verify property exits\", function() {\r",
							"    pm.expect(pm.response.json()[0]).to.have.property('Productname')\r",
							"})\r",
							"\r",
							"pm.test(\"verify substring\", function () {\r",
							"    pm.expect(pm.response.text()).to.include(\"Productcount\")\r",
							"})\r",
							"\r",
							""
						],
						"type": "text/javascript",
						"packages": {},
						"requests": {}
					}
				}
			],
			"request": {
				"method": "GET",
				"header": [],
				"url": {
					"raw": "https://69243c3a3ad095fb84734718.mockapi.io/carts",
					"protocol": "https",
					"host": [
						"69243c3a3ad095fb84734718",
						"mockapi",
						"io"
					],
					"path": [
						"carts"
					]
				}
			},
			"response": []
		},
		{
			"name": "post id",
			"event": [
				{
					"listen": "test",
					"script": {
						"exec": [
							"pm.collectionVariables.set(\"id\", pm.response.json().id)\r",
							"\r",
							"pm.test(\"status code verify\",function()\r",
							"{\r",
							"    pm.response.to.have.status(201);\r",
							"});\r",
							"pm.test(\"status message verify\" ,function()\r",
							"{\r",
							"    pm.response.to.have.status(\"Created\");\r",
							"});\r",
							"pm.test(\"status code within range\", function () {\r",
							"    pm.expect(pm.response.code).to.be.within(200, 404);\r",
							"});\r",
							"pm.test(\"Range of the status code verify\", function()\r",
							"{\r",
							"    pm.expect(pm.response.code).to.be.oneOf([200,201,205]);\r",
							"})\r",
							"pm.test(\"status code below verify\", function()\r",
							"{\r",
							"    pm.expect(pm.response.code).to.be.below(202);\r",
							"})\r",
							"pm.test(\"status code above verify\", function()\r",
							"{\r",
							"    pm.expect(pm.response.code).to.be.above(199);\r",
							"})\r",
							"pm.test(\"Verify response time\", function()\r",
							"{\r",
							"    pm.expect(pm.response.responseTime).to.be.below(3000);\r",
							"})\r",
							"pm.test(\"Verify response time\", function()\r",
							"{\r",
							"    pm.expect(pm.response.responseTime).to.be.above(200);\r",
							"})\r",
							"pm.test(\"check content type header is present\" , function()\r",
							"{\r",
							"    pm.response.to.have.header(\"Content-type\");\r",
							"})\r",
							"pm.test(\"check value of content-type\" , function()\r",
							"{\r",
							"    pm.expect(pm.response.headers.get(\"Content-type\")).to.eql(\"application/json\");\r",
							"})\r",
							"pm.test(\"check vaue of content-type\" , function()\r",
							"{\r",
							"    pm.expect(pm.response.headers.get(\"Content-type\")).to.include(\"son\");\r",
							"})\r",
							"pm.test(\"check multiple headers\", function() {\r",
							"    const data = [\"content-length\", \"content-type\", \"date\"]\r",
							"    data.forEach(function(item) {\r",
							"        pm.response.to.have.header(item);\r",
							"    })\r",
							"})\r",
							"pm.test(\"test status code using if-else\", function() {\r",
							"    const data = pm.response.code\r",
							"    if (data === 201) {\r",
							"        pm.response.to.have.status(\"Created\")\r",
							"    } else {\r",
							"        pm.response.to.have.status(\"Not Found\")\r",
							"    }\r",
							"})\r",
							"\r",
							"pm.test(\"status code is not in oneof function\", function() {\r",
							"    pm.expect(pm.response.code).to.not.be.oneOf([ 202, 203, 204, 205, 206, 207]);\r",
							"})\r",
							"\r",
							"pm.test(\"content-length value check\", function() {\r",
							"    let data = pm.response.headers.get(\"content-length\")\r",
							"    pm.expect(Number(data)).to.not.eql(0)\r",
							"})\r",
							"\r",
							"\r",
							"// test response body:\r",
							"pm.test(\"response exist or not\", function() {\r",
							"    pm.expect(pm.response.text()).to.not.be.empty\r",
							"})\r",
							"\r",
							"pm.test(\"verify property exits\", function() {\r",
							"    pm.expect(pm.response.json()).to.have.property('Productname')\r",
							"})\r",
							"\r",
							"pm.test(\"verify substring\", function () {\r",
							"    pm.expect(pm.response.text()).to.include(\"Productcount\")\r",
							"})\r",
							"\r",
							""
						],
						"type": "text/javascript",
						"packages": {},
						"requests": {}
					}
				}
			],
			"request": {
				"method": "POST",
				"header": [],
				"body": {
					"mode": "raw",
					"raw": "{\r\n    \"Productname\": \"Recycled Aluminum Sausages\",\r\n    \"Productcount\": 72,\r\n    \"id\": \"56\"\r\n}",
					"options": {
						"raw": {
							"language": "json"
						}
					}
				},
				"url": {
					"raw": "https://69243c3a3ad095fb84734718.mockapi.io/carts",
					"protocol": "https",
					"host": [
						"69243c3a3ad095fb84734718",
						"mockapi",
						"io"
					],
					"path": [
						"carts"
					]
				}
			},
			"response": []
		},
		{
			"name": "get id",
			"event": [
				{
					"listen": "test",
					"script": {
						"exec": [
							"pm.collectionVariables.set(\"id\", pm.response.json().id)\r",
							"\r",
							"pm.test(\"status code verify\",function()\r",
							"{\r",
							"    pm.response.to.have.status(200);\r",
							"});\r",
							"pm.test(\"status message verify\" ,function()\r",
							"{\r",
							"    pm.response.to.have.status(\"OK\");\r",
							"});\r",
							"pm.test(\"status code within range\", function () {\r",
							"    pm.expect(pm.response.code).to.be.within(200, 404);\r",
							"});\r",
							"pm.test(\"Range of the status code verify\", function()\r",
							"{\r",
							"    pm.expect(pm.response.code).to.be.oneOf([200,201,205]);\r",
							"})\r",
							"pm.test(\"status code below verify\", function()\r",
							"{\r",
							"    pm.expect(pm.response.code).to.be.below(202);\r",
							"})\r",
							"pm.test(\"status code above verify\", function()\r",
							"{\r",
							"    pm.expect(pm.response.code).to.be.above(199);\r",
							"})\r",
							"pm.test(\"Verify response time\", function()\r",
							"{\r",
							"    pm.expect(pm.response.responseTime).to.be.below(3000);\r",
							"})\r",
							"pm.test(\"Verify response time\", function()\r",
							"{\r",
							"    pm.expect(pm.response.responseTime).to.be.above(200);\r",
							"})\r",
							"pm.test(\"check content type header is present\" , function()\r",
							"{\r",
							"    pm.response.to.have.header(\"Content-type\");\r",
							"})\r",
							"pm.test(\"check value of content-type\" , function()\r",
							"{\r",
							"    pm.expect(pm.response.headers.get(\"Content-type\")).to.eql(\"application/json\");\r",
							"})\r",
							"pm.test(\"check vaue of content-type\" , function()\r",
							"{\r",
							"    pm.expect(pm.response.headers.get(\"Content-type\")).to.include(\"son\");\r",
							"})\r",
							"pm.test(\"check multiple headers\", function() {\r",
							"    const data = [\"content-length\", \"content-type\", \"date\"]\r",
							"    data.forEach(function(item) {\r",
							"        pm.response.to.have.header(item);\r",
							"    })\r",
							"})\r",
							"pm.test(\"test status code using if-else\", function() {\r",
							"    const data = pm.response.code\r",
							"    if (data === 200) {\r",
							"        pm.response.to.have.status(\"OK\")\r",
							"    } else {\r",
							"        pm.response.to.have.status(\"Not Found\")\r",
							"    }\r",
							"})\r",
							"\r",
							"pm.test(\"status code is not in oneof function\", function() {\r",
							"    pm.expect(pm.response.code).to.not.be.oneOf([ 202, 203, 204, 205, 206, 207]);\r",
							"})\r",
							"\r",
							"pm.test(\"content-length value check\", function() {\r",
							"    let data = pm.response.headers.get(\"content-length\")\r",
							"    pm.expect(Number(data)).to.not.eql(0)\r",
							"})\r",
							"\r",
							"\r",
							"// test response body:\r",
							"pm.test(\"response exist or not\", function() {\r",
							"    pm.expect(pm.response.text()).to.not.be.empty\r",
							"})\r",
							"\r",
							"pm.test(\"verify property exits\", function() {\r",
							"    pm.expect(pm.response.json()).to.have.property('Productname')\r",
							"})\r",
							"\r",
							"pm.test(\"verify substring\", function () {\r",
							"    pm.expect(pm.response.text()).to.include(\"Productcount\")\r",
							"})\r",
							"\r",
							""
						],
						"type": "text/javascript",
						"packages": {},
						"requests": {}
					}
				}
			],
			"request": {
				"method": "GET",
				"header": [],
				"url": {
					"raw": "https://69243c3a3ad095fb84734718.mockapi.io/carts/{{id}}",
					"protocol": "https",
					"host": [
						"69243c3a3ad095fb84734718",
						"mockapi",
						"io"
					],
					"path": [
						"carts",
						"{{id}}"
					]
				}
			},
			"response": []
		},
		{
			"name": "put id",
			"event": [
				{
					"listen": "test",
					"script": {
						"exec": [
							"pm.collectionVariables.set(\"id\", pm.response.json().id)\r",
							"\r",
							"pm.test(\"status code verify\",function()\r",
							"{\r",
							"    pm.response.to.have.status(200);\r",
							"});\r",
							"pm.test(\"status message verify\" ,function()\r",
							"{\r",
							"    pm.response.to.have.status(\"OK\");\r",
							"});\r",
							"pm.test(\"status code within range\", function () {\r",
							"    pm.expect(pm.response.code).to.be.within(200, 404);\r",
							"});\r",
							"pm.test(\"Range of the status code verify\", function()\r",
							"{\r",
							"    pm.expect(pm.response.code).to.be.oneOf([200,201,205]);\r",
							"})\r",
							"pm.test(\"status code below verify\", function()\r",
							"{\r",
							"    pm.expect(pm.response.code).to.be.below(202);\r",
							"})\r",
							"pm.test(\"status code above verify\", function()\r",
							"{\r",
							"    pm.expect(pm.response.code).to.be.above(199);\r",
							"})\r",
							"pm.test(\"Verify response time\", function()\r",
							"{\r",
							"    pm.expect(pm.response.responseTime).to.be.below(3000);\r",
							"})\r",
							"pm.test(\"Verify response time\", function()\r",
							"{\r",
							"    pm.expect(pm.response.responseTime).to.be.above(200);\r",
							"})\r",
							"pm.test(\"check content type header is present\" , function()\r",
							"{\r",
							"    pm.response.to.have.header(\"Content-type\");\r",
							"})\r",
							"pm.test(\"check value of content-type\" , function()\r",
							"{\r",
							"    pm.expect(pm.response.headers.get(\"Content-type\")).to.eql(\"application/json\");\r",
							"})\r",
							"pm.test(\"check vaue of content-type\" , function()\r",
							"{\r",
							"    pm.expect(pm.response.headers.get(\"Content-type\")).to.include(\"son\");\r",
							"})\r",
							"pm.test(\"check multiple headers\", function() {\r",
							"    const data = [\"content-length\", \"content-type\", \"date\"]\r",
							"    data.forEach(function(item) {\r",
							"        pm.response.to.have.header(item);\r",
							"    })\r",
							"})\r",
							"pm.test(\"test status code using if-else\", function() {\r",
							"    const data = pm.response.code\r",
							"    if (data === 200) {\r",
							"        pm.response.to.have.status(\"OK\")\r",
							"    } else {\r",
							"        pm.response.to.have.status(\"Not Found\")\r",
							"    }\r",
							"})\r",
							"\r",
							"pm.test(\"status code is not in oneof function\", function() {\r",
							"    pm.expect(pm.response.code).to.not.be.oneOf([ 202, 203, 204, 205, 206, 207]);\r",
							"})\r",
							"\r",
							"pm.test(\"content-length value check\", function() {\r",
							"    let data = pm.response.headers.get(\"content-length\")\r",
							"    pm.expect(Number(data)).to.not.eql(0)\r",
							"})\r",
							"\r",
							"\r",
							"// test response body:\r",
							"pm.test(\"response exist or not\", function() {\r",
							"    pm.expect(pm.response.text()).to.not.be.empty\r",
							"})\r",
							"\r",
							"pm.test(\"verify property exits\", function() {\r",
							"    pm.expect(pm.response.json()).to.have.property('Productname')\r",
							"})\r",
							"\r",
							"pm.test(\"verify substring\", function () {\r",
							"    pm.expect(pm.response.text()).to.include(\"Productcount\")\r",
							"})\r",
							"\r",
							""
						],
						"type": "text/javascript",
						"packages": {},
						"requests": {}
					}
				}
			],
			"request": {
				"method": "PUT",
				"header": [],
				"url": {
					"raw": "https://69243c3a3ad095fb84734718.mockapi.io/carts/{{id}}",
					"protocol": "https",
					"host": [
						"69243c3a3ad095fb84734718",
						"mockapi",
						"io"
					],
					"path": [
						"carts",
						"{{id}}"
					]
				}
			},
			"response": []
		},
		{
			"name": "delete id",
			"event": [
				{
					"listen": "test",
					"script": {
						"exec": [
							"pm.collectionVariables.set(\"id\", pm.response.json().id)\r",
							"\r",
							"pm.test(\"status code verify\",function()\r",
							"{\r",
							"    pm.response.to.have.status(200);\r",
							"});\r",
							"pm.test(\"status message verify\" ,function()\r",
							"{\r",
							"    pm.response.to.have.status(\"OK\");\r",
							"});\r",
							"pm.test(\"status code within range\", function () {\r",
							"    pm.expect(pm.response.code).to.be.within(200, 404);\r",
							"});\r",
							"pm.test(\"Range of the status code verify\", function()\r",
							"{\r",
							"    pm.expect(pm.response.code).to.be.oneOf([200,201,205]);\r",
							"})\r",
							"pm.test(\"status code below verify\", function()\r",
							"{\r",
							"    pm.expect(pm.response.code).to.be.below(202);\r",
							"})\r",
							"pm.test(\"status code above verify\", function()\r",
							"{\r",
							"    pm.expect(pm.response.code).to.be.above(199);\r",
							"})\r",
							"pm.test(\"Verify response time\", function()\r",
							"{\r",
							"    pm.expect(pm.response.responseTime).to.be.below(3000);\r",
							"})\r",
							"pm.test(\"Verify response time\", function()\r",
							"{\r",
							"    pm.expect(pm.response.responseTime).to.be.above(200);\r",
							"})\r",
							"pm.test(\"check content type header is present\" , function()\r",
							"{\r",
							"    pm.response.to.have.header(\"Content-type\");\r",
							"})\r",
							"pm.test(\"check value of content-type\" , function()\r",
							"{\r",
							"    pm.expect(pm.response.headers.get(\"Content-type\")).to.eql(\"application/json\");\r",
							"})\r",
							"pm.test(\"check vaue of content-type\" , function()\r",
							"{\r",
							"    pm.expect(pm.response.headers.get(\"Content-type\")).to.include(\"son\");\r",
							"})\r",
							"pm.test(\"check multiple headers\", function() {\r",
							"    const data = [\"content-length\", \"content-type\", \"date\"]\r",
							"    data.forEach(function(item) {\r",
							"        pm.response.to.have.header(item);\r",
							"    })\r",
							"})\r",
							"pm.test(\"test status code using if-else\", function() {\r",
							"    const data = pm.response.code\r",
							"    if (data === 200) {\r",
							"        pm.response.to.have.status(\"OK\")\r",
							"    } else {\r",
							"        pm.response.to.have.status(\"Not Found\")\r",
							"    }\r",
							"})\r",
							"\r",
							"pm.test(\"status code is not in oneof function\", function() {\r",
							"    pm.expect(pm.response.code).to.not.be.oneOf([ 202, 203, 204, 205, 206, 207]);\r",
							"})\r",
							"\r",
							"pm.test(\"content-length value check\", function() {\r",
							"    let data = pm.response.headers.get(\"content-length\")\r",
							"    pm.expect(Number(data)).to.not.eql(0)\r",
							"})\r",
							"\r",
							"\r",
							"// test response body:\r",
							"pm.test(\"response exist or not\", function() {\r",
							"    pm.expect(pm.response.text()).to.not.be.empty\r",
							"})\r",
							"\r",
							"pm.test(\"verify property exits\", function() {\r",
							"    pm.expect(pm.response.json()).to.have.property('Productname')\r",
							"})\r",
							"\r",
							"pm.test(\"verify substring\", function () {\r",
							"    pm.expect(pm.response.text()).to.include(\"Productcount\")\r",
							"})\r",
							"\r",
							""
						],
						"type": "text/javascript",
						"packages": {},
						"requests": {}
					}
				}
			],
			"request": {
				"method": "DELETE",
				"header": [],
				"url": {
					"raw": "https://69243c3a3ad095fb84734718.mockapi.io/carts/{{id}}",
					"protocol": "https",
					"host": [
						"69243c3a3ad095fb84734718",
						"mockapi",
						"io"
					],
					"path": [
						"carts",
						"{{id}}"
					]
				}
			},
			"response": []
		}
	],
	"event": [
		{
			"listen": "prerequest",
			"script": {
				"type": "text/javascript",
				"packages": {},
				"requests": {},
				"exec": [
					""
				]
			}
		},
		{
			"listen": "test",
			"script": {
				"type": "text/javascript",
				"packages": {},
				"requests": {},
				"exec": [
					""
				]
			}
		}
	],
	"variable": [
		{
			"key": "id",
			"value": "60"
		}
	]
}